rest_framework_jsonmask/__init__.py
rest_framework_jsonmask/constants.py
rest_framework_jsonmask/decorators.py
rest_framework_jsonmask/serializers.py
rest_framework_jsonmask/utils.py
rest_framework_jsonmask/views.py
djangorestframework_jsonmask-0.1.1.dist-info/LICENSE
djangorestframework_jsonmask-0.1.1.dist-info/METADATA
djangorestframework_jsonmask-0.1.1.dist-info/WHEEL
djangorestframework_jsonmask-0.1.1.dist-info/top_level.txt
djangorestframework_jsonmask-0.1.1.dist-info/RECORD
