Metadata-Version: 2.1
Name: djangorestframework-jsonmask
Version: 0.1.1
Summary: Implements Google's partial response in Django RestFramework
Home-page: https://github.com/zapier/django-rest-framework-jsonmask
Author: Craig Labenz
Author-email: craig.labenz@zapier.com
License: BSD
Download-URL: https://github.com/zapier/django-rest-framework-jsonmask/tarball/0.1.1
Platform: UNKNOWN
Classifier: Development Status :: 4 - Beta
Classifier: Environment :: Web Environment
Classifier: Framework :: Django
Classifier: Framework :: Django :: 1.11
Classifier: Framework :: Django :: 2.0
Classifier: Framework :: Django :: 2.1
Classifier: Intended Audience :: Developers
Classifier: License :: OSI Approved :: BSD License
Classifier: Operating System :: OS Independent
Classifier: Natural Language :: English
Classifier: Programming Language :: Python :: 2
Classifier: Programming Language :: Python :: 2.7
Classifier: Programming Language :: Python :: 3
Classifier: Programming Language :: Python :: 3.5
Classifier: Programming Language :: Python :: 3.6
Classifier: Programming Language :: Python :: 3.7
Classifier: Topic :: Internet :: WWW/HTTP
Classifier: Topic :: Software Development :: Libraries :: Python Modules
Requires-Dist: jsonmask
Requires-Dist: Django (>=1.11)
Requires-Dist: djangorestframework (>=3.5)
